bitformat/__init__.py
bitformat/_array.py
bitformat/_bits.py
bitformat/_common.py
bitformat/_dtype_definitions.py
bitformat/_dtypes.py
bitformat/_field.py
bitformat/_fieldtype.py
bitformat/_format.py
bitformat/_if.py
bitformat/_let.py
bitformat/_options.py
bitformat/_pass.py
bitformat/_reader.py
bitformat/_repeat.py
bitformat/_version.py
bitformat/_while.py
bitformat/bitformat_grammar.lark
bitformat/py.typed
bitformat/rust.abi3.so
bitformat.libs/libgcc_s-d8c0fe17.so.1
bitformat-0.9.0.dist-info/METADATA
bitformat-0.9.0.dist-info/WHEEL
bitformat-0.9.0.dist-info/RECORD
bitformat-0.9.0.dist-info/licenses/LICENSE
