Metadata-Version: 2.4
Name: bitformat
Version: 0.9.0
Classifier: Development Status :: 4 - Beta
Classifier: Intended Audience :: Developers
Classifier: Operating System :: OS Independent
Classifier: Programming Language :: Python :: 3.11
Classifier: Programming Language :: Python :: 3.12
Classifier: Programming Language :: Python :: 3.13
Classifier: Programming Language :: Python :: 3.14
Classifier: Programming Language :: Rust
Classifier: Programming Language :: Python :: Implementation :: CPython
Classifier: License :: OSI Approved :: MIT License
Classifier: Topic :: Software Development :: Libraries :: Python Modules
Classifier: Topic :: File Formats
Classifier: Typing :: Typed
Requires-Dist: lark>=1.2.2,<1.3.0
Requires-Dist: pytest>=7.4.2 ; extra == 'dev'
Requires-Dist: hypothesis>=6.98.13 ; extra == 'dev'
Requires-Dist: pytest-benchmark>=4.0.0 ; extra == 'dev'
Requires-Dist: pyright>=1.1.389 ; extra == 'dev'
Requires-Dist: pytest-cov>=6.0.0 ; extra == 'dev'
Requires-Dist: build ; extra == 'dev'
Provides-Extra: dev
License-File: LICENSE
Summary: A Python library for creating and parsing binary formats.
Author-email: Scott Griffiths <dr.scottgriffiths@gmail.com>
Requires-Python: >=3.11
Project-URL: homepage, https://github.com/scott-griffiths/bitformat
Project-URL: documentation, https://bitformat.readthedocs.io/
